octalearn_poetry/__init__.py
octalearn_poetry/hello.py
octalearn_poetry-0.2.0.dist-info/WHEEL
octalearn_poetry-0.2.0.dist-info/METADATA
octalearn_poetry-0.2.0.dist-info/RECORD
